tinker_cookbook/__init__.py
tinker_cookbook/checkpoint_utils.py
tinker_cookbook/cli_utils.py
tinker_cookbook/completers.py
tinker_cookbook/display.py
tinker_cookbook/hyperparam_utils.py
tinker_cookbook/model_info.py
tinker_cookbook/renderers.py
tinker_cookbook/tokenizer_utils.py
tinker_cookbook/chat_app/README.md
tinker_cookbook/chat_app/tinker_chat_cli.py
tinker_cookbook/distillation/datasets.py
tinker_cookbook/distillation/train_on_policy.py
tinker_cookbook/eval/README.md
tinker_cookbook/eval/custom_evaluators.py
tinker_cookbook/eval/custom_inspect_task.py
tinker_cookbook/eval/evaluators.py
tinker_cookbook/eval/inspect_evaluators.py
tinker_cookbook/eval/inspect_utils.py
tinker_cookbook/eval/run_inspect_evals.py
tinker_cookbook/example_data/conversations.jsonl
tinker_cookbook/example_data/multilingual.txt
tinker_cookbook/preference/comparison_policy_evaluator.py
tinker_cookbook/preference/dpo_datasets.py
tinker_cookbook/preference/preference_datasets.py
tinker_cookbook/preference/train_dpo.py
tinker_cookbook/preference/types.py
tinker_cookbook/recipes/README.md
tinker_cookbook/recipes/rl_basic.py
tinker_cookbook/recipes/rl_loop.py
tinker_cookbook/recipes/sl_basic.py
tinker_cookbook/recipes/sl_loop.py
tinker_cookbook/recipes/chat_sl/README.md
tinker_cookbook/recipes/chat_sl/chat_datasets.py
tinker_cookbook/recipes/chat_sl/train.py
tinker_cookbook/recipes/code_rl/README.md
tinker_cookbook/recipes/code_rl/code_env.py
tinker_cookbook/recipes/code_rl/code_grading.py
tinker_cookbook/recipes/code_rl/lcb_utils.py
tinker_cookbook/recipes/code_rl/train.py
tinker_cookbook/recipes/code_rl/sandbox_config/local.yaml
tinker_cookbook/recipes/distillation/README.md
tinker_cookbook/recipes/distillation/off_policy_reasoning.py
tinker_cookbook/recipes/distillation/on_policy_distillation.py
tinker_cookbook/recipes/distillation/on_policy_multi_teacher.py
tinker_cookbook/recipes/math_rl/README.md
tinker_cookbook/recipes/math_rl/arithmetic_env.py
tinker_cookbook-0.1.0.dist-info/METADATA
tinker_cookbook-0.1.0.dist-info/WHEEL
tinker_cookbook-0.1.0.dist-info/licenses/LICENSE
tinker_cookbook-0.1.0.dist-info/RECORD
