Metadata-Version: 2.4
Name: tinker_cookbook
Version: 0.1.0
Summary: Implementations of post-training algorithms using the Tinker API
Project-URL: Homepage, https://thinkingmachines.ai/tinker
Project-URL: Repository, https://github.com/thinking-machines-lab/tinker
Project-URL: Documentation, https://tinker-docs.thinkingmachines.ai/
Author-email: Tinker authors <tinker@thinkingmachines.ai>
License-File: LICENSE
Requires-Python: >=3.11
Requires-Dist: anyio
Requires-Dist: blobfile
Requires-Dist: chz
Requires-Dist: cloudpickle
Requires-Dist: datasets
Requires-Dist: inspect-ai
Requires-Dist: math-verify
Requires-Dist: numpy
Requires-Dist: pylatexenc
Requires-Dist: rich
Requires-Dist: scipy
Requires-Dist: sympy
Requires-Dist: termcolor
Requires-Dist: textarena>=0.7.4
Requires-Dist: tinker>=0.6.1
Requires-Dist: torch
Requires-Dist: transformers
Provides-Extra: all
Requires-Dist: chromadb; extra == 'all'
Requires-Dist: google-genai; extra == 'all'
Requires-Dist: huggingface-hub; extra == 'all'
Requires-Dist: neptune-scale>=0.27.0; extra == 'all'
Requires-Dist: openai; extra == 'all'
Requires-Dist: trackio<1.0.0; extra == 'all'
Requires-Dist: verifiers>=0.1.8.post0; extra == 'all'
Requires-Dist: wandb; extra == 'all'
Provides-Extra: dev
Requires-Dist: pyright; extra == 'dev'
Requires-Dist: pytest; extra == 'dev'
Requires-Dist: pytest-asyncio; extra == 'dev'
Requires-Dist: ruff; extra == 'dev'
Provides-Extra: neptune-scale
Requires-Dist: neptune-scale>=0.27.0; extra == 'neptune-scale'
Provides-Extra: trackio
Requires-Dist: trackio<1.0.0; extra == 'trackio'
Provides-Extra: vector-search
Requires-Dist: chromadb; extra == 'vector-search'
Requires-Dist: google-genai; extra == 'vector-search'
Requires-Dist: huggingface-hub; extra == 'vector-search'
Provides-Extra: verifiers
Requires-Dist: openai; extra == 'verifiers'
Requires-Dist: verifiers>=0.1.8.post0; extra == 'verifiers'
Provides-Extra: wandb
Requires-Dist: wandb; extra == 'wandb'
